crypty/__init__.py
crypty/main.py
crypty-0.0.6.dist-info/METADATA
crypty-0.0.6.dist-info/RECORD
crypty-0.0.6.dist-info/WHEEL
crypty-0.0.6.dist-info/top_level.txt
