Metadata-Version: 2.1
Name: crypty
Version: 0.0.6
Summary: Encrypt and decrypt text easily
Home-page: https://github.com/foreverfighter/crypty
Author: Yi Sheng Siow
Author-email: siowyisheng@gmail.com
License: UNKNOWN
Platform: UNKNOWN
Classifier: Programming Language :: Python :: 3
Classifier: License :: OSI Approved :: MIT License
Classifier: Operating System :: OS Independent
Requires-Dist: cryptography
